{
 "absolute_value": 0,
 "align_labels_right": 0,
 "creation": "2025-03-28 10:57:46.337291",
 "custom_format": 1,
 "default_print_language": "en",
 "disabled": 0,
 "doc_type": "Increment Letter",
 "docstatus": 0,
 "doctype": "Print Format",
 "font_size": 14,
 "html": "<p>{{frappe.utils.formatdate(doc.date)}}</p>\n<p>TO</p>\n<p>{{doc.salutation}} {{doc.employee_name}}</p>\n<p>{{doc.designation}}</p>\n\n\n<p>Dear {{doc.employee_name}}</p>\n\n<p>Subject: Letter of Increment</p>\n\n<p>This year has been eventful and challenging for all of us. We have been working on the huge challenge of scaling up our business and growing our bottom line.</p>\n\n<p>Consequent to the review of your performance during the period <strong>{{frappe.utils.formatdate(doc.from_date)}} To {{frappe.utils.formatdate(doc.to_date)}}</strong> we take great pleasure to inform that your annual CTC has been increased to <strong>RS. {{doc.new_ctc_amount}}</strong> the breakup of which is given in <strong>Annexure 1</strong>, w.e.f. {{frappe.utils.formatdate(doc.effective_date)}}.\n</p>\n\n\n<p><strong>All the other terms and conditions remain unchanged as per your Appointment Letter</strong></p>\n<p>We are sure you will make best use of the opportunity offered to you and contribute substantially to the success of our organization as you have done in the past and fully justify the confidence placed in you by the management.</p>\n<p><strong>Please sign the duplicate copy of this letter as a token of acceptance of the same.</strong></p>\n<p>With Best Wishes,</p>\n\n<p><strong>I have received a copy of this letter and have read and understood its contents.</strong></p>\n<p>Name:</p>\n<p>Signature:</p>\n<p>Date:</p>\n\n\n<p><strong>Annexure 1</strong></p>\n<p>Your revised salary and perquisites will be as under:</p>\n{% set earnings_totals = namespace(monthly=0, yearly=0) %}\n\n<table class=\"table table-bordered\">\n    <thead>\n        <tr>\n            <th style=\"width: 50%;\">Component</th>\n            <th style=\"text-align: right;\">Monthly</th>\n            <th style=\"text-align: right;\">Yearly</th>\n        </tr>\n    </thead>\n    <tbody>\n        {% for row in doc.earnings %}\n        <tr>\n            <td>{{ row.earning or '' }}</td>\n            <td style=\"text-align: right;\">{{ row.monthly or 0 }}</td>\n            <td style=\"text-align: right;\">{{ row.yearly or 0 }}</td>\n        </tr>\n        {% set earnings_totals.monthly = earnings_totals.monthly + (row.monthly or 0) %}\n        {% set earnings_totals.yearly = earnings_totals.yearly + (row.yearly or 0) %}\n        {% endfor %}\n\n        <tr>\n            <th>Total</th>\n            <th style=\"text-align: right;\">{{ earnings_totals.monthly }}</th>\n            <th style=\"text-align: right;\">{{ earnings_totals.yearly }}</th>\n        </tr>\n    </tbody>\n</table>\n\n\n\n{% set deductions_totals = namespace(monthly=0, yearly=0) %}\n\n<table class=\"table table-bordered\">\n    <thead>\n        <tr>\n            <th style=\"width: 50%;\">Deduction Component</th>\n            <th style=\"text-align: right;\">Monthly</th>\n            <th style=\"text-align: right;\">Yearly</th>\n        </tr>\n    </thead>\n    <tbody>\n        {% for row in doc.deductions %}\n        <tr>\n            <td>{{ row.deduction or '' }}</td>\n            <td style=\"text-align: right;\">{{ row.monthly or 0 }}</td>\n            <td style=\"text-align: right;\">{{ row.yearly or 0 }}</td>\n        </tr>\n        {% set deductions_totals.monthly = deductions_totals.monthly + (row.monthly or 0) %}\n        {% set deductions_totals.yearly = deductions_totals.yearly + (row.yearly or 0) %}\n        {% endfor %}\n\n        <tr>\n            <th>Total</th>\n            <th style=\"text-align: right;\">{{ deductions_totals.monthly }}</th>\n            <th style=\"text-align: right;\">{{ deductions_totals.yearly }}</th>\n        </tr>\n    </tbody>\n</table>\n\n\n{% set employer_totals = namespace(monthly=0, yearly=0) %}\n\n<table class=\"table table-bordered\">\n    <thead>\n        <tr>\n            <th style=\"width: 50%;\">Employer Contribution</th>\n            <th style=\"text-align: right;\">Monthly</th>\n            <th style=\"text-align: right;\">Yearly</th>\n        </tr>\n    </thead>\n    <tbody>\n        {% for row in doc.contribution_from_employer %}\n        <tr>\n            <td>{{ row.contribution_from_employer or '' }}</td>\n            <td style=\"text-align: right;\">{{ row.monthly or 0 }}</td>\n            <td style=\"text-align: right;\">{{ row.yearly or 0 }}</td>\n        </tr>\n        {% set employer_totals.monthly = employer_totals.monthly + (row.monthly or 0) %}\n        {% set employer_totals.yearly = employer_totals.yearly + (row.yearly or 0) %}\n        {% endfor %}\n\n        <tr>\n            <th>Total</th>\n            <th style=\"text-align: right;\">{{ employer_totals.monthly }}</th>\n            <th style=\"text-align: right;\">{{ employer_totals.yearly }}</th>\n        </tr>\n    </tbody>\n</table>\n\n{% set total_ctc = (earnings_totals.yearly or 0) + (employer_totals.yearly or 0) %}\n\n<p><strong>Total CTC:</strong> {{ total_ctc }}</p>\n\n<p>I have received a copy of this letter and have read and understood its contents.</p>\n<P>Name:</P>\n<p>Signature:</p>\n<p>Date:</p>\n",
 "idx": 0,
 "line_breaks": 0,
 "margin_bottom": 15.0,
 "margin_left": 15.0,
 "margin_right": 15.0,
 "margin_top": 15.0,
 "modified": "2025-03-28 16:44:39.590828",
 "modified_by": "Administrator",
 "module": "Mohan Impex",
 "name": "MI  Increment Letter",
 "owner": "Administrator",
 "page_number": "Hide",
 "print_format_builder": 0,
 "print_format_builder_beta": 0,
 "print_format_type": "JS",
 "raw_printing": 0,
 "show_section_headings": 0,
 "standard": "Yes"
}