{
 "actions": [],
 "allow_rename": 1,
 "creation": "2025-04-04 18:20:13.931493",
 "doctype": "DocType",
 "engine": "InnoDB",
 "field_order": [
  "section_break_dedt"
 ],
 "fields": [
  {
   "fieldname": "section_break_dedt",
   "fieldtype": "Section Break"
  }
 ],
 "index_web_pages_for_search": 1,
 "istable": 1,
 "links": [],
 "modified": "2025-05-13 17:06:50.665210",
 "modified_by": "Administrator",
 "module": "Mohan Impex",
 "name": "Product Category Price",
 "owner": "Administrator",
 "permissions": [],
 "sort_field": "modified",
 "sort_order": "DESC",
 "states": []
}